{"name":"update3","new_project_tasks":{"k374":{"name":"k374","release_time":180,"deadline_time":360,"processing_time":4,"requirements":[],"project":"p45"},"k375":{"name":"k375","release_time":203,"deadline_time":487,"processing_time":2,"requirements":[],"project":"p45"},"k376":{"name":"k376","release_time":203,"deadline_time":487,"processing_time":10,"requirements":["k375"],"project":"p45"},"k377":{"name":"k377","release_time":210,"deadline_time":627,"processing_time":8,"requirements":[],"project":"p45"},"k378":{"name":"k378","release_time":212,"deadline_time":770,"processing_time":7,"requirements":[],"project":"p45"},"k379":{"name":"k379","release_time":212,"deadline_time":770,"processing_time":3,"requirements":["k378"],"project":"p45"},"k380":{"name":"k380","release_time":234,"deadline_time":443,"processing_time":4,"requirements":[],"project":"p45"},"k381":{"name":"k381","release_time":234,"deadline_time":443,"processing_time":7,"requirements":["k380"],"project":"p45"},"k382":{"name":"k382","release_time":244,"deadline_time":394,"processing_time":8,"requirements":[],"project":"p45"},"k383":{"name":"k383","release_time":259,"deadline_time":1009,"processing_time":3,"requirements":[],"project":"p45"},"k384":{"name":"k384","release_time":259,"deadline_time":1009,"processing_time":10,"requirements":["k383"],"project":"p45"},"k385":{"name":"k385","release_time":267,"deadline_time":396,"processing_time":2,"requirements":[],"project":"p45"},"k404":{"name":"k404","release_time":184,"deadline_time":1327,"processing_time":4,"requirements":[],"project":"p49"},"k405":{"name":"k405","release_time":184,"deadline_time":1327,"processing_time":13,"requirements":["k404"],"project":"p49"},"k406":{"name":"k406","release_time":184,"deadline_time":1327,"processing_time":4,"requirements":["k405"],"project":"p49"},"k407":{"name":"k407","release_time":184,"deadline_time":1327,"processing_time":13,"requirements":["k405"],"project":"p49"},"k408":{"name":"k408","release_time":227,"deadline_time":415,"processing_time":4,"requirements":[],"project":"p49"},"k409":{"name":"k409","release_time":191,"deadline_time":288,"processing_time":4,"requirements":[],"project":"p50"},"k410":{"name":"k410","release_time":196,"deadline_time":1255,"processing_time":6,"requirements":[],"project":"p50"},"k411":{"name":"k411","release_time":196,"deadline_time":1255,"processing_time":5,"requirements":["k410"],"project":"p50"},"k412":{"name":"k412","release_time":196,"deadline_time":1255,"processing_time":8,"requirements":["k410"],"project":"p50"},"k413":{"name":"k413","release_time":196,"deadline_time":1255,"processing_time":4,"requirements":["k411"],"project":"p50"},"k414":{"name":"k414","release_time":187,"deadline_time":1043,"processing_time":6,"requirements":[],"project":"p51"},"k415":{"name":"k415","release_time":187,"deadline_time":1043,"processing_time":12,"requirements":["k414"],"project":"p51"},"k416":{"name":"k416","release_time":211,"deadline_time":355,"processing_time":4,"requirements":[],"project":"p51"},"k417":{"name":"k417","release_time":222,"deadline_time":547,"processing_time":10,"requirements":[],"project":"p51"},"k418":{"name":"k418","release_time":225,"deadline_time":567,"processing_time":4,"requirements":[],"project":"p51"},"k419":{"name":"k419","release_time":226,"deadline_time":1192,"processing_time":12,"requirements":[],"project":"p51"},"k420":{"name":"k420","release_time":226,"deadline_time":1192,"processing_time":15,"requirements":["k419"],"project":"p51"},"k421":{"name":"k421","release_time":226,"deadline_time":1192,"processing_time":8,"requirements":["k420"],"project":"p51"},"k422":{"name":"k422","release_time":190,"deadline_time":515,"processing_time":5,"requirements":[],"project":"p52"},"k423":{"name":"k423","release_time":202,"deadline_time":1113,"processing_time":8,"requirements":[],"project":"p52"},"k424":{"name":"k424","release_time":202,"deadline_time":1113,"processing_time":12,"requirements":["k423"],"project":"p52"},"k425":{"name":"k425","release_time":203,"deadline_time":418,"processing_time":14,"requirements":[],"project":"p52"},"k426":{"name":"k426","release_time":203,"deadline_time":418,"processing_time":5,"requirements":["k425"],"project":"p52"},"k427":{"name":"k427","release_time":216,"deadline_time":920,"processing_time":8,"requirements":[],"project":"p52"},"k428":{"name":"k428","release_time":216,"deadline_time":920,"processing_time":12,"requirements":["k427"],"project":"p52"},"k429":{"name":"k429","release_time":239,"deadline_time":564,"processing_time":7,"requirements":[],"project":"p52"},"k430":{"name":"k430","release_time":195,"deadline_time":520,"processing_time":4,"requirements":[],"project":"p53"},"k431":{"name":"k431","release_time":195,"deadline_time":520,"processing_time":5,"requirements":["k430"],"project":"p53"},"k432":{"name":"k432","release_time":205,"deadline_time":341,"processing_time":4,"requirements":[],"project":"p53"},"k433":{"name":"k433","release_time":204,"deadline_time":590,"processing_time":8,"requirements":[],"project":"p53"},"k434":{"name":"k434","release_time":204,"deadline_time":590,"processing_time":6,"requirements":["k433"],"project":"p53"},"k435":{"name":"k435","release_time":224,"deadline_time":1053,"processing_time":4,"requirements":[],"project":"p53"},"k436":{"name":"k436","release_time":224,"deadline_time":1053,"processing_time":8,"requirements":["k435"],"project":"p53"},"k437":{"name":"k437","release_time":246,"deadline_time":644,"processing_time":4,"requirements":[],"project":"p53"},"k438":{"name":"k438","release_time":252,"deadline_time":637,"processing_time":11,"requirements":[],"project":"p53"},"k439":{"name":"k439","release_time":247,"deadline_time":362,"processing_time":3,"requirements":[],"project":"p53"},"k440":{"name":"k440","release_time":260,"deadline_time":426,"processing_time":3,"requirements":[],"project":"p53"},"k441":{"name":"k441","release_time":277,"deadline_time":647,"processing_time":2,"requirements":[],"project":"p53"},"k442":{"name":"k442","release_time":277,"deadline_time":647,"processing_time":7,"requirements":["k441"],"project":"p53"},"k443":{"name":"k443","release_time":282,"deadline_time":879,"processing_time":7,"requirements":[],"project":"p53"},"k444":{"name":"k444","release_time":282,"deadline_time":879,"processing_time":10,"requirements":["k443"],"project":"p53"},"k445":{"name":"k445","release_time":183,"deadline_time":1801,"processing_time":7,"requirements":[],"project":"p54"},"k446":{"name":"k446","release_time":183,"deadline_time":1801,"processing_time":4,"requirements":["k445"],"project":"p54"},"k447":{"name":"k447","release_time":183,"deadline_time":1801,"processing_time":10,"requirements":["k445"],"project":"p54"},"k448":{"name":"k448","release_time":183,"deadline_time":1801,"processing_time":3,"requirements":["k446"],"project":"p54"},"k449":{"name":"k449","release_time":183,"deadline_time":1801,"processing_time":4,"requirements":["k446"],"project":"p54"}},"new_projects":{"p45":{"name":"p45","task_names":["k374","k385","k383","k382","k378","k377","k384","k381","k375","k376","k380","k379"],"allowed_workers":["w11","w0","w12","w13","w4","w9","w2","w1"]},"p49":{"name":"p49","task_names":["k405","k408","k404","k406","k407"],"allowed_workers":["w3","w11","w0","w12","w13","w4","w2"]},"p50":{"name":"p50","task_names":["k409","k410","k413","k412","k411"],"allowed_workers":["w3","w0","w7","w12"]},"p51":{"name":"p51","task_names":["k416","k420","k421","k414","k419","k415","k418","k417"],"allowed_workers":["w7","w9","w11","w12"]},"p52":{"name":"p52","task_names":["k422","k423","k425","k427","k428","k429","k426","k424"],"allowed_workers":["w3","w11","w0","w7","w4","w9","w2","w14"]},"p53":{"name":"p53","task_names":["k437","k443","k444","k434","k436","k442","k439","k441","k432","k433","k431","k438","k430","k435","k440"],"allowed_workers":["w3","w11","w12","w0","w7","w13","w5"]},"p54":{"name":"p54","task_names":["k449","k446","k447","k448","k445"],"allowed_workers":["w3","w6","w11","w12","w0","w7","w4","w9","w2"]}},"new_meeting_tasks":{"m52":{"name":"m52","release_time":260,"deadline_time":283,"processing_time":4,"requirements":[],"worker_names":["w14","w6","w13","w5","w3"]},"m53":{"name":"m53","release_time":266,"deadline_time":286,"processing_time":3,"requirements":[],"worker_names":["w12","w7","w0","w14","w10","w5","w13","w1","w8","w2","w11","w4","w9","w6","w3"]},"m54":{"name":"m54","release_time":310,"deadline_time":339,"processing_time":4,"requirements":[],"worker_names":["w12","w9","w11","w14","w7","w10","w1","w6","w13","w4","w8","w5","w2","w3"]}},"new_trainings":{"tr10":{"name":"tr10","worker_name":"w10","task_pool":["k304","k86","k316","k368","k305","k165","k89","k174","k147","k34","k449","k448","k447","k446","k445"],"min_duration":30},"tr11":{"name":"tr11","worker_name":"w3","task_pool":["k222","k377","k218","k217","k188","k18","k118","k418","k173","k354","k414","k416","k415","k417"],"min_duration":16}}}